loggerflow/__init__.py
loggerflow/excepthook.py
loggerflow/loggerflow.py
loggerflow/traceback_backlighter.py
loggerflow/backends/__init__.py
loggerflow/backends/abstract_backend.py
loggerflow/backends/discord.py
loggerflow/backends/file.py
loggerflow/backends/telegram.py
loggerflow/exceptions/__init__.py
loggerflow/lifecycle/__init__.py
loggerflow/lifecycle/lifecycle_cli.py
loggerflow/lifecycle/lifecycle_server.py
loggerflow/lifecycle/database/__init__.py
loggerflow/lifecycle/database/models.py
loggerflow/lifecycle/database/queries.py
loggerflow/lifecycle/routes/__init__.py
loggerflow/lifecycle/routes/site.py
loggerflow/lifecycle/routes/webhooks.py
loggerflow/lifecycle/routes/websockets.py
loggerflow/lifecycle/static/bone.svg
loggerflow/lifecycle/static/broken_bone.svg
loggerflow/lifecycle/static/green_power.svg
loggerflow/lifecycle/static/hidden.svg
loggerflow/lifecycle/static/loggerflow.png
loggerflow/lifecycle/static/loggerflow.svg
loggerflow/lifecycle/static/loggerflow_bowl.svg
loggerflow/lifecycle/static/loggerflow_red_eye.svg
loggerflow/lifecycle/static/loggerflow_white.svg
loggerflow/lifecycle/static/paw_prints.svg
loggerflow/lifecycle/static/red_power.svg
loggerflow/lifecycle/static/settings.svg
loggerflow/lifecycle/static/settings_white.svg
loggerflow/lifecycle/static/css/bootstrap.min.css
loggerflow/lifecycle/static/css/exceptions.css
loggerflow/lifecycle/static/css/loggerflow.css
loggerflow/lifecycle/static/css/pagination.css
loggerflow/lifecycle/static/css/progress.css
loggerflow/lifecycle/static/css/welcome.css
loggerflow/lifecycle/static/js/bootstrap.bundle.min.js
loggerflow/lifecycle/static/js/jquery-3.6.4.min.js
loggerflow/lifecycle/static/js/loggerflow.js
loggerflow/lifecycle/static/js/loggerflow_functions.js
loggerflow/lifecycle/templates/alarms.html
loggerflow/lifecycle/templates/base.html
loggerflow/lifecycle/templates/exceptions.html
loggerflow/lifecycle/templates/hidden.html
loggerflow/lifecycle/templates/loggerflow.html
loggerflow-0.0.6.dist-info/LICENSE
loggerflow-0.0.6.dist-info/METADATA
loggerflow-0.0.6.dist-info/WHEEL
loggerflow-0.0.6.dist-info/entry_points.txt
loggerflow-0.0.6.dist-info/top_level.txt
loggerflow-0.0.6.dist-info/RECORD
