Metadata-Version: 2.1
Name: loggerflow
Version: 0.0.6
Summary: Simple and fast solution of bug tracking for your Python projects and backlight project lines in traceback.
Home-page: https://github.com/DeNRuDi/loggerflow
Author: DeNRuDi
Author-email: denisrudnitskiy0@gmail.com
Classifier: Development Status :: 4 - Beta
Classifier: Intended Audience :: Developers
Classifier: Operating System :: OS Independent
Classifier: License :: OSI Approved :: MIT License
Classifier: Programming Language :: Python :: 3
Classifier: Programming Language :: Python :: 3.7
Classifier: Programming Language :: Python :: 3.8
Classifier: Programming Language :: Python :: 3.9
Classifier: Programming Language :: Python :: 3.10
Classifier: Programming Language :: Python :: 3.11
Classifier: Programming Language :: Python :: 3.12
License-File: LICENSE
Requires-Dist: requests
Requires-Dist: discordwebhook
Requires-Dist: fastapi
Requires-Dist: aiohttp
Requires-Dist: aiofiles
Requires-Dist: uvicorn[standard]
Requires-Dist: jinja2
Requires-Dist: aiosqlite
Requires-Dist: sqlalchemy
Requires-Dist: psutil
Requires-Dist: pydantic-settings
Requires-Dist: python-multipart
